Workbook

Sheet Summary
B2: AFCONS INFRASTRUCTURE LIMITED
B3: Equity Research — Investment Summary
B5: INVESTMENT RECOMMENDATION
B7: Recommendation: | C7: =Valuation!E83 -> HOLD
B8: Target Price (Blended): | C8: =Valuation!E79 -> 349.56217
B9: Current Market Price: | C9: =Valuation!C40 -> 305.45
B10: Upside / (Downside): | C10: =Valuation!E82 -> 0.14441698
B13: MARKET DATA
B14: Shares Outstanding (Cr): | C14: =Valuation!C38 -> 36.798
B15: Market Cap (₹ Cr): | C15: =Valuation!C40*Valuation!C38 -> 11239.949
B16: Net Debt FY26 (₹ Cr): | C16: =Historicals!G216-Historicals!G225 -> 2652.38
B17: Enterprise Value (₹ Cr): | C17: =C15+C16 -> 13892.329
B20: FINANCIAL SUMMARY (₹ Cr)
C21: FY23A | D21: FY24A | E21: FY25A | F21: FY26A | G21: FY27E | H21: FY28E | I21: FY29E
B22: Revenue from Operations | C22: =Historicals!D8 -> 12637.38 | D22: =Historicals!E8 -> 13267.5 | E22: =Historicals!F8 -> 12548.42 | F22: =Historicals!G8 -> 11948.38 | G22: =Projections!E40 -> 10011.261 | H22: =Projections!F40 -> 12118.851 | I22: =Projections!G40 -> 14725.412
B23: YoY Growth % | D23: =D22/C22-1 -> 0.049861601 | E23: =E22/D22-1 -> -0.054198606 | F23: =F22/E22-1 -> -0.047817972 | G23: =G22/F22-1 -> -0.16212402 | H23: =H22/G22-1 -> 0.21052194 | I23: =I22/H22-1 -> 0.21508319
B24: EBITDA (excl Other Income) | C24: =Historicals!D210 -> 1310.61 | D24: =Historicals!E210 -> 1365.03 | E24: =Historicals!F210 -> 1355.96 | F24: =Historicals!G210 -> 1217.11 | G24: =Projections!E58 -> 1051.1824 | H24: =Projections!F58 -> 1393.6678 | I24: =Projections!G58 -> 1722.8732
B25: EBITDA Margin % | C25: =C24/C22 -> 0.103709 | D25: =D24/D22 -> 0.10288525 | E25: =E24/E22 -> 0.10805823 | F25: =F24/F22 -> 0.10186402 | G25: =G24/G22 -> 0.105 | H25: =H24/H22 -> 0.115 | I25: =I24/I22 -> 0.117
B26: PAT | C26: =Historicals!D31 -> 410.86 | D26: =Historicals!E31 -> 449.76 | E26: =Historicals!F31 -> 486.79 | F26: =Historicals!G31 -> 250.74 | G26: =Projections!E70 -> 431.7658 | H26: =Projections!F70 -> 697.0955 | I26: =Projections!G70 -> 968.31549
B27: EPS (₹) | C27: =Historicals!D51 -> 12.06 | D27: =Historicals!E51 -> 13.2 | E27: =Historicals!F51 -> 13.24 | F27: =Historicals!G51 -> 6.82 | G27: =Projections!E72 -> 11.733404 | H27: =Projections!F72 -> 18.943842 | I27: =Projections!G72 -> 26.314351
B28: Closing Order Book | C28: =Historicals!D243 -> 30406 | D28: =Historicals!E243 -> 30961 | E28: =Historicals!F243 -> 36868.61 | F28: =Historicals!G243 -> 32495.65 | G28: =Projections!E9 -> 36395.128 | H28: =Projections!F9 -> 42946.251 | I28: =Projections!G9 -> 49388.189
B29: Book-to-Bill (x) | C29: =C28/C22 -> 2.4060367 | D29: =D28/D22 -> 2.3335971 | E29: =E28/E22 -> 2.9381077 | F29: =F28/F22 -> 2.7196699 | G29: =G28/G22 -> 3.6354191 | H29: =H28/H22 -> 3.5437561 | I29: =I28/I22 -> 3.3539428
B32: VALUATION SNAPSHOT
B33: Method | C33: Implied Price (₹) | D33: Weight | E33: Contribution (₹)
B34: DCF | C34: =Valuation!C39 -> 359.41576 | D34: =Valuation!D75 -> 0.4 | E34: =C34*D34 -> 143.7663
B35: EV/EBITDA (FY28E) | C35: =Valuation!E68 -> 344.52867 | D35: =Valuation!D76 -> 0.3 | E35: =C35*D35 -> 103.3586
B36: P/E (FY28E) | C36: =Valuation!E69 -> 378.87684 | D36: =Valuation!D77 -> 0.2 | E36: =C36*D36 -> 75.775369
B37: P/B (FY26) | C37: =Valuation!E70 -> 266.61895 | D37: =Valuation!D78 -> 0.1 | E37: =C37*D37 -> 26.661895
B38: BLENDED TARGET | C38: =Valuation!E79 -> 349.56217 | D38: =SUM(D34:D37) -> 1 | E38: =SUM(E34:E37) -> 349.56217
B41: INVESTMENT THESIS
B42: Positives
B43: • Mgmt guidance ₹30,000 Cr inflow FY27 (vs FY26 ₹4,125 Cr) — recovery trajectory
B44: • Specialty EPC moat: Marine, Underground Metro, Hydro (peer-leading margins ~12% vs sector 8.5%)
B45: • Diversified OB ₹32,500 Cr — 2.7x book-to-bill provides multi-year visibility
B46: • Post-IPO balance sheet flexibility — improving credit profile, supplier negotiation leverage
B47: • Underpenetrated overseas opportunity (Africa, Middle East marine pipeline in L1)
B49: Risks
B50: • Geopolitical risk on overseas execution (FY26 Africa disruptions affected calibration)
B51: • Working capital intensive: ~118 days NWC FY26, contract assets ₹7,731 Cr (largest item)
B52: • Government client payment cycles — receivables stretched to 123 days FY26
B53: • Sub-contract intensity 42% of revenue limits operating leverage on cost base
... B57: KEY MODEL ASSUMPTIONS
B58: Total OB Growth FY27/28/29 | D58: 12% / 18% / 15%
B59: FY26 Baseline Execution Rate | D59: 32.4% (FY26 Rev ÷ Mar'25 OB)
B60: Cost of Debt | D60: 10.5% (constant per user)
B61: Tax Rate | D61: 25.5% (concessional regime)
B62: WACC / Terminal Growth | D62: 12.3% / 4.0%
B63: Working Capital approach | D63: Days × Revenue ÷ 365 per line item, mgmt commentary
B64: EBITDA definition | D64: Bottom-up from cost lines, excludes Other Income
B65: Finance cost basis | D65: Total Debt incl WC loans × constant CoD × Avg balance
B67: SOURCES
B68: • Afcons Q4 FY26 Investor Presentation & Earnings Call (May 2026)
B69: • Afcons Q4 FY25 Investor Presentation & Earnings Call (May 2025)
B70: • Afcons RHP (October 2024)
B71: • BSE/NSE filings for peer multiples (May 2026)
B72: • Damodaran India ERP 2026 dataset

Sheet Historicals
B2: AFCONS INFRASTRUCTURE — CONSOLIDATED HISTORICALS
B3: Every line item as reported. FY23 from AR 2022-23. FY24-26 from quarterly outcomes/Q4 IPs. ₹ Cr.
D5: FY23A | E5: FY24A | F5: FY25A | G5: FY26A | H5: Source
B6: CONSOLIDATED STATEMENT OF PROFIT AND LOSS (₹ Cr)
B7: Income
B8: Revenue from Operations | D8: 12637.38 | E8: 13267.5 | F8: 12548.42 | G8: 11948.38 | H8: FY23 AR; FY24-26 outcomes
B9: Other income (net) | D9: 206.71 | E9: 379.38 | F9: 474.35 | G9: 373.72 | H9: As reported
B10: Total Income | D10: =SUM(D8:D9) -> 12844.09 | E10: =SUM(E8:E9) -> 13646.88 | F10: =SUM(F8:F9) -> 13022.77 | G10: =SUM(G8:G9) -> 12322.1 | H10: Sum
B12: Expenses
B13: Cost of material consumed | D13: 3851.71 | E13: 4012.48 | F13: 3290.14 | G13: 2845.17 | H13: As reported
B14: Cost of Construction | D14: 5200.65 | E14: 5293.97 | F14: 5246.06 | G14: 5046.17 | H14: As reported
B15: Employee benefit expenses | D15: 1298.23 | E15: 1383.42 | F15: 1435.11 | G15: 1451.72 | H15: As reported
B16: Finance costs | D16: 446.66 | E16: 577.26 | F16: 629.2 | G16: 673.61 | H16: As reported
B17: Depreciation and amortisation expense | D17: 471.58 | E17: 494.53 | F17: 491.1 | G17: 453.92 | H17: As reported
B18: Other expenses | D18: 976.18 | E18: 1212.6 | F18: 1221.15 | G18: 1388.21 | H18: As reported
B19: Total Expenses | D19: =SUM(D13:D18) -> 12245.01 | E19: =SUM(E13:E18) -> 12974.26 | F19: =SUM(F13:F18) -> 12312.76 | G19: =SUM(G13:G18) -> 11858.8 | H19: Sum
B21: Profit before exceptional items & tax | D21: =D10-D19 -> 599.08 | E21: =E10-E19 -> 672.62 | F21: =F10-F19 -> 710.01 | G21: =G10-G19 -> 463.3 | H21: Total Income − Total Expenses
B22: Exceptional Items | D22: 0 | E22: 0 | F22: 0 | G22: 76.51 | H22: FY26: ₹76.51 Cr Labour Code
B23: Profit before tax | D23: =D21-D22 -> 599.08 | E23: =E21-E22 -> 672.62 | F23: =F21-F22 -> 710.01 | G23: =G21-G22 -> 386.79 | H23: PBEI − Exceptional
B25: Tax expense:
B26: (i) Current tax | D26: 189.43 | E26: 200.24 | F26: 275.93 | G26: 198.71 | H26: As reported
B27: (ii) Deferred tax − (credit) / charge | D27: -29.79 | E27: 7.24 | F27: -36.78 | G27: -64.86 | H27: As reported (negative = credit)
B28: (iii) Tax expense relating to earlier years (net) | D28: 28.58 | E28: 15.38 | F28: -15.93 | G28: 2.2 | H28: As reported
B29: Total tax expense | D29: =SUM(D26:D28) -> 188.22 | E29: =SUM(E26:E28) -> 222.86 | F29: =SUM(F26:F28) -> 223.22 | G29: =SUM(G26:G28) -> 136.05 | H29: Sum of (i)+(ii)+(iii)
B31: Profit after tax and exceptional items | D31: =D23-D29 -> 410.86 | E31: =E23-E29 -> 449.76 | F31: =F23-F29 -> 486.79 | G31: =G23-G29 -> 250.74 | H31: PBT − Tax
B33: Other Comprehensive Income (OCI)
B34: A) Items that will not be reclassified to P&L
B35: (a) Changes in fair value of equity investments (FVOCI), net of tax | D35: -0.4 | E35: 0.26 | F35: 0.01 | G35: -0.23 | H35: As reported
B36: (b) Remeasurements of defined benefit plans, net of tax | D36: -2.1 | E36: -8.51 | F36: -5.74 | G36: 15.94 | H36: As reported
B37: B) Items that will be reclassified to P&L
B38: (a) Exchange differences on translation of foreign operations | D38: 66.16 | E38: 7.59 | F38: -4.02 | G38: -7.38 | H38: As reported
B39: Other Comprehensive Income / (Loss) | D39: =SUM(D35:D38) -> 63.66 | E39: =SUM(E35:E38) -> -0.66 | F39: =SUM(F35:F38) -> -9.75 | G39: =SUM(G35:G38) -> 8.33 | H39: Sum
B41: Total Comprehensive Income for the year | D41: =D31+D39 -> 474.52 | E41: =E31+E39 -> 449.1 | F41: =F31+F39 -> 477.04 | G41: =G31+G39 -> 259.07 | H41: PAT + OCI
B43: Profit attributable to:
B44: − Owners of the Company | D44: 410.87 | E44: 449.76 | F44: 486.81 | G44: 251.5 | H44: As reported
B45: − Non-controlling interest | D45: -0.01 | E45: 0 | F45: -0.02 | G45: -0.76 | H45: As reported
B47: Paid-up equity share capital | D47: 71.97 | E47: 340.74 | F47: 367.78 | G47: 367.78 | H47: As reported (FV ₹10 each)
B48: Other equity (reserves) | D48: 2653.72 | E48: 3255.21 | F48: 4892.74 | G48: 5082.02 | H48: As reported
B50: Earnings per share (₹):
B51: Basic EPS | D51: 12.06 | E51: 13.2 | F51: 13.24 | G51: 6.82 | H51: As reported
B52: Diluted EPS | D52: 12.06 | E52: 13.2 | F52: 13.24 | G52: 6.82 | H52: As reported
B54: P&L HYGIENE — Reported vs Model
B55: Reported PAT (Owners + NCI from filings) | D55: 410.86 | E55: 449.76 | F55: 486.79 | G55: 250.74
B56: Model PAT (row 31) | D56: =D31 -> 410.86 | E56: =E31 -> 449.76 | F56: =F31 -> 486.79 | G56: =G31 -> 250.74
B57: Variance (Model − Reported) | D57: =D56-D55 -> -1.9326762e-12 | E57: =E56-E55 -> 0 | F57: =F56-F55 -> 0 | G57: =G56-G55 -> -2.5579538e-12 | H57: Should be ≤ ₹0.05 Cr (rounding)
B60: CONSOLIDATED BALANCE SHEET (₹ Cr)
D61: FY23A | E61: FY24A | F61: FY25A | G61: FY26A | H61: Note
B62: A. ASSETS
B63: 1. Non-current assets
B64: (a) Property, plant and equipment | D64: 2448.75 | E64: 2715.14 | F64: 2630.86 | G64: 2410.37
B65: (b) Capital work-in-progress | D65: 183.6 | E65: 43.07 | F65: 32.85 | G65: 901.01 | H65: FY26 spike: TBM addition
B66: (c) Right-of-use assets | D66: 48.72 | E66: 67.91 | F66: 106.43 | G66: 87.96
B67: (d) Goodwill | D67: 0.14 | E67: 0.14 | F67: 0.14 | G67: 0.14
B68: (e) Intangible assets | D68: 0.61 | E68: 0.6 | F68: 0.55 | G68: 0.5
B69: (f) Financial assets:
B70: (i) Investments | D70: 0.5 | E70: 0.77 | F70: 0.78 | G70: 0.54
B71: (ii) Trade receivables | D71: 651.22 | E71: 499.2 | F71: 678.91 | G71: 606.57
B72: (iii) Other financial assets | D72: 365.92 | E72: 417.99 | F72: 441.93 | G72: 429.2
B73: (g) Contract assets (Non-current) | D73: 1416.49 | E73: 1271.01 | F73: 1646.58 | G73: 1497.04
B74: (h) Non-current tax assets (net) | D74: 28.8 | E74: 53.64 | F74: 12.22 | G74: 62.33
B75: (i) Other non-current assets | D75: 181.54 | E75: 190.88 | F75: 212 | G75: 181.25
B76: Total non-current assets | D76: =SUM(D64:D75) -> 5326.29 | E76: =SUM(E64:E75) -> 5260.35 | F76: =SUM(F64:F75) -> 5763.25 | G76: =SUM(G64:G75) -> 6176.91 | H76: Sum
B78: 2. Current assets
B79: (a) Inventories | D79: 1585.79 | E79: 1626.56 | F79: 1010.22 | G79: 1016.57
B80: (b) Financial assets:
B81: (i) Trade receivables | D81: 2196.63 | E81: 3120.99 | F81: 2779.32 | G81: 3431.52
B82: (ii) Cash and cash equivalents | D82: 319.32 | E82: 413.26 | F82: 440.17 | G82: 385.7
B83: (iii) Bank balances other than (ii) above | D83: 58.12 | E83: 253 | F83: 330.39 | G83: 500.19
B84: (iv) Loans | D84: 53.35 | E84: 61.83 | F84: 57.18 | G84: 67.93
B85: (v) Other financial assets | D85: 398.31 | E85: 501.34 | F85: 209.3 | G85: 209.54
B86: (c) Contract assets (Current) | D86: 3272.51 | E86: 3954.39 | F86: 5449.18 | G86: 6234.46
B87: (d) Other current assets | D87: 1090.92 | E87: 1041.92 | F87: 1080.21 | G87: 1108.06
B88: Total current assets | D88: =SUM(D79:D87) -> 8974.95 | E88: =SUM(E79:E87) -> 10973.29 | F88: =SUM(F79:F87) -> 11355.97 | G88: =SUM(G79:G87) -> 12953.97 | H88: Sum
B90: TOTAL ASSETS (1+2) | D90: =D76+D88 -> 14301.24 | E90: =E76+E88 -> 16233.64 | F90: =F76+F88 -> 17119.22 | G90: =G76+G88 -> 19130.88 | H90: Non-current + Current
B92: B. EQUITY AND LIABILITIES
B93: 1. Equity
B94: (a) Equity share capital | D94: 71.97 | E94: 340.74 | F94: 367.78 | G94: 367.78
B95: (b) Instruments entirely equity in nature (Pref shares) | D95: 450 | E95: 0 | F95: 0 | G95: 0 | H95: Pref shares converted/cancelled pre-IPO
B96: (c) Other equity | D96: 2653.72 | E96: 3255.21 | F96: 4892.74 | G96: 5082.02
B97: Equity attributable to shareholders | D97: =SUM(D94:D96) -> 3175.69 | E97: =SUM(E94:E96) -> 3595.95 | F97: =SUM(F94:F96) -> 5260.52 | G97: =SUM(G94:G96) -> 5449.8 | H97: Sum
B98: Non-controlling interest | D98: 1.56 | E98: 1.56 | F98: 1.54 | G98: 0.78
B99: Total Equity | D99: =D97+D98 -> 3177.25 | E99: =E97+E98 -> 3597.51 | F99: =F97+F98 -> 5262.06 | G99: =G97+G98 -> 5450.58 | H99: Equity attributable + NCI
B101: 2. Liabilities
B102: (A) Non-current liabilities
B103: (a) Financial liabilities:
B104: (i) Borrowings (NC) | D104: 596.48 | E104: 597.69 | F104: 595.24 | G104: 919.6
B105: (ii) Lease Liabilities (NC) | D105: 15.68 | E105: 35.15 | F105: 58.28 | G105: 49.53
B106: (iii) Trade payables (NC):
B107: (a) Due to micro and small enterprises (NC) | D107: 51.95 | E107: 23.21 | F107: 14.58 | G107: 17.27
B108: (b) Due to other creditors (NC) | D108: 420.89 | E108: 407.79 | F108: 419.2 | G108: 410.64
B109: (iv) Other financial liabilities (NC) | D109: 156.88 | E109: 126.53 | F109: 74.84 | G109: 54.32
B110: (b) Contract liabilities (NC) | D110: 1524.03 | E110: 1451.29 | F110: 2270.76 | G110: 2141.31
B111: (c) Provisions (NC) | D111: 8.87 | E111: 9.31 | F111: 24.55 | G111: 70.74
B112: (d) Deferred tax liabilities (net) | D112: 99.29 | E112: 103.67 | F112: 64.96 | G112: 5.46
B113: Total non-current liabilities | D113: =SUM(D104:D112) -> 2874.07 | E113: =SUM(E104:E112) -> 2754.64 | F113: =SUM(F104:F112) -> 3522.41 | G113: =SUM(G104:G112) -> 3668.87 | H113: Sum
B115: (B) Current liabilities
B116: (a) Financial liabilities:
B117: (i) Borrowings (C) | D117: 966.35 | E117: 1857.32 | F117: 1640.48 | G117: 2618.67
B118: (ii) Lease Liabilities (C) | D118: 33.75 | E118: 33.08 | F118: 49.3 | G118: 39.11
B119: (iii) Trade payables (C):
...

Sheet Projections
B2: AFCONS INFRASTRUCTURE — PROJECTIONS
B3: FY27E-FY29E. ₹ Crore. Blue = inputs (flex these). Black = formulas. Green = links from Historicals.
D5: FY26A | E5: FY27E | F5: FY28E | G5: FY29E | H5: Driver / Reasoning
B6: ORDER BOOK FORECAST (₹ Cr)
B8: Total OB Growth % YoY | E8: 0.12 | F8: 0.18 | G8: 0.15 | H8: FY27: mgmt guided ₹30k Cr inflow → ~12% OB growth. FY28-29: ramp on bigger order book.
B9: Closing Total Order Book | D9: =Historicals!G243 -> 32495.65 | E9: =D9*(1+E8) -> 36395.128 | F9: =E9*(1+F8) -> 42946.251 | G9: =F9*(1+G8) -> 49388.189
B11: Segment OB Composition % (Forecast — flex these)
B12: Marine & Industrial | D12: =Historicals!G253 -> 0.15 | E12: 0.15 | F12: 0.14 | G12: 0.13 | H12: Marine: Overseas-heavy (Africa, Middle East). FY27 normalise from FY26 spike, slight moderation
B13: Surface Transport | D13: =Historicals!G254 -> 0.09 | E13: 0.09 | F13: 0.1 | G13: 0.1 | H13: Surface: Mgmt 'selective bidding' — share stays low. Slight uptick FY28+
B14: Urban Infra (Metro) | D14: =Historicals!G255 -> 0.28 | E14: 0.28 | F14: 0.29 | G14: 0.3 | H14: Metro: Mgmt highlighted Delhi MRTS Phase IV, Bangalore Metro pipeline → grows
B15: Urban Infra (Bridges) | D15: =Historicals!G256 -> 0.23 | E15: 0.23 | F15: 0.23 | G15: 0.23 | H15: Bridges: RRTS, elevated corridors. Stable share
B16: Hydro & Underground | D16: =Historicals!G257 -> 0.23 | E16: 0.23 | F16: 0.22 | G16: 0.22 | H16: Hydro: Mgmt cited Jamrani Dam, Basania Dam wins → roughly stable
B17: Oil & Gas | D17: =Historicals!G258 -> 0.02 | E17: 0.02 | F17: 0.02 | G17: 0.02 | H17: O&G: Mgmt 'small but selective'. Stays at 2%
B18: Sum (=100%) | D18: =SUM(D12:D17) -> 1 | E18: =SUM(E12:E17) -> 1 | F18: =SUM(F12:F17) -> 1 | G18: =SUM(G12:G17) -> 1
B20: EXECUTION RATE BUILD
B22: FY26 Baseline Execution Rate (Rev / Opening OB) | D22: =Historicals!G8/Historicals!F243 -> 0.32408002 | H22: Baseline = FY26 Revenue ÷ FY25 closing OB
B24: Segment Execution Adjustment (pp vs baseline) — flex these
B25: Marine & Industrial | E25: -0.03 | F25: 0.01 | G25: 0.02 | H25: FY27 -3pp: heavy overseas exposure (Africa) — geopolitical drag persists. FY28-29: recovery.
B26: Surface Transport | E26: -0.02 | F26: 0 | G26: 0.01 | H26: FY27 -2pp: mgmt cited 'selective bidding'; new contracts ramp slower. FY28-29: modest improvement.
B27: Urban Infra (Metro) | E27: -0.01 | F27: 0.01 | G27: 0.02 | H27: FY27 -1pp: HSR & metro execution continues but slower start on FY27 new wins. Recovery FY28-29.
B28: Urban Infra (Bridges) | E28: -0.01 | F28: 0.01 | G28: 0.02 | H28: FY27 -1pp: similar to Metro — ramp lag. Recovery FY28-29.
B29: Hydro & Underground | E29: -0.02 | F29: 0.01 | G29: 0.02 | H29: FY27 -2pp: Hydro/tunnels are long-cycle; new wins (Jamrani, Basania) take time to ramp.
B30: Oil & Gas | E30: 0 | F30: 0 | G30: 0.01 | H30: FY27 0pp: small base, mgmt 'selective' — stable execution rate.
B32: Weighted Avg Execution Adjustment
B33: Weighted Adjustment (weighted by opening OB share) | E33: =SUMPRODUCT(E25:E30,D12:D17) -> -0.016 | F33: =SUMPRODUCT(F25:F30,E12:E17) -> 0.0089 | G33: =SUMPRODUCT(G25:G30,F12:F17) -> 0.0188 | H33: Σ(segment adjustment × prior-year OB share)
B35: Final Execution Rate (Baseline + Weighted Adj) | D35: =D22 -> 0.32408002 | E35: =$D$22+E33 -> 0.30808002 | F35: =$D$22+F33 -> 0.33298002 | G35: =$D$22+G33 -> 0.34288002 | H35: FY26 Baseline + Weighted Adjustment
B38: PROJECTED P&L (₹ Cr)
B40: Revenue from Operations | D40: =Historicals!G8 -> 11948.38 | E40: =D9*E35 -> 10011.261 | F40: =E9*F35 -> 12118.851 | G40: =F9*G35 -> 14725.412 | H40: Opening OB times Execution Rate
B41: YoY Growth % | E41: =E40/D40-1 -> -0.16212402 | F41: =F40/E40-1 -> 0.21052194 | G41: =G40/F40-1 -> 0.21508319
B42: Other Income | D42: =Historicals!G9 -> 373.72 | E42: =E40*0.03 -> 300.33782 | F42: =F40*0.03 -> 363.56552 | G42: =G40*0.03 -> 441.76235 | H42: FY27-29: 3.0% of Revenue from Ops (steady-state treasury income)
B43: Total Income | D43: =D40+D42 -> 12322.1 | E43: =E40+E42 -> 10311.598 | F43: =F40+F42 -> 12482.416 | G43: =G40+G42 -> 15167.174
B45: Operating Expenses (forecasted as % of Revenue from Ops)
B46: Cost of Material Consumed (% Revenue) | D46: =Historicals!G11/Historicals!G8 -> 0 | E46: 0.245 | F46: 0.24 | G46: 0.24 | H46: FY26 base 23.8%. Mgmt: 'procurement scale + better commodity hedging' → modest improvement. Stable from FY28.
B47: Cost of Construction (Sub-contract) (% Revenue) | D47: =Historicals!G12/Historicals!G8 -> 0 | E47: 0.42 | F47: 0.42 | G47: 0.42 | H47: FY26 base 42.2%. Mgmt: 'sub-contract intensity stable'. Held flat — biggest cost line, low operating leverage.
B48: Employee Expenses (% Revenue) | D48: =Historicals!G13/Historicals!G8 -> 0.23812182 | E48: 0.115 | F48: 0.11 | G48: 0.108 | H48: FY26 base 12.2%. Mgmt: 'employee cost grows slower than revenue as we scale'. Operating leverage on fixed staff.
B49: Other Expenses (% Revenue) | D49: =Historicals!G14/Historicals!G8 -> 0.42233089 | E49: 0.115 | F49: 0.115 | G49: 0.115 | H49: FY26 base 12.9%. Labour code drag (~60bps) FY26. FY27-29: normalize as labour code base-effect washes out.
B51: Cost Lines (₹ Cr) = % × Revenue from Ops
B52: Cost of Material Consumed | D52: =Historicals!G11 -> 0 | E52: =E46*E40 -> 2452.7589 | F52: =F46*F40 -> 2908.5241 | G52: =G46*G40 -> 3534.0988
B53: Cost of Construction | D53: =Historicals!G12 -> 0 | E53: =E47*E40 -> 4204.7295 | F53: =F47*F40 -> 5089.9172 | G53: =G47*G40 -> 6184.6729
B54: Employee Expenses | D54: =Historicals!G13 -> 2845.17 | E54: =E48*E40 -> 1151.295 | F54: =F48*F40 -> 1333.0736 | G54: =G48*G40 -> 1590.3444
B55: Other Expenses | D55: =Historicals!G14 -> 5046.17 | E55: =E49*E40 -> 1151.295 | F55: =F49*F40 -> 1393.6678 | G55: =G49*G40 -> 1693.4223
B56: Total Operating Expenses | D56: =SUM(D52:D55) -> 7891.34 | E56: =SUM(E52:E55) -> 8960.0783 | F56: =SUM(F52:F55) -> 10725.183 | G56: =SUM(G52:G55) -> 13002.538
B58: EBITDA | D58: =D40-D56 -> 4057.04 | E58: =E40-E56 -> 1051.1824 | F58: =F40-F56 -> 1393.6678 | G58: =G40-G56 -> 1722.8732 | H58: Revenue from Ops - OpEx (NOT incl Other Income)
B59: EBITDA Margin (% of Revenue from Ops) | D59: =D58/D40 -> 0.33954729 | E59: =E58/E40 -> 0.105 | F59: =F58/F40 -> 0.115 | G59: =G58/G40 -> 0.117 | H59: OUTPUT (not input) — derived from cost build
B61: Depreciation & Amortization | D61: =Historicals!G17 -> 453.92 | E61: =E40*0.04 -> 400.45042 | F61: =F40*0.038 -> 460.51632 | G61: =G40*0.036 -> 530.11482 | H61: FY27-29: 4.0%/3.8%/3.6% of Rev. FY26 ₹725 Cr capex per mgmt guidance → higher D&A FY27
B62: EBIT | D62: =D58+D42-D61 -> 3976.84 | E62: =E58+E42-E61 -> 951.06976 | F62: =F58+F42-F61 -> 1296.717 | G62: =G58+G42-G61 -> 1634.5207 | H62: EBITDA + Other Income - D&A
B64: Finance Cost | D64: =Historicals!G16 -> 673.61 | E64: =E65*(D85+E85)/2 -> 371.51835 | F64: =F65*(E85+F85)/2 -> 361.01835 | G64: =G65*(F85+G85)/2 -> 334.76835 | H64: Constant CoD times Average Debt (Opening + Closing) divided by 2
B65: (Cost of Debt assumption — kept constant) | E65: 0.105 | F65: =E65 -> 0.105 | G65: =F65 -> 0.105 | H65: Per user direction: kept constant at 10.5% (finance cost incl WC loans). No RBI cycle adjustments.
B66: Exceptional Items | D66: =Historicals!G22 -> 76.51 | E66: 0 | F66: 0 | G66: 0
B67: Profit Before Tax | D67: =D62-D64-D66 -> 3226.72 | E67: =E62-E64-E66 -> 579.55141 | F67: =F62-F64-F66 -> 935.69866 | G67: =G62-G64-G66 -> 1299.7523
B68: Tax Expense | D68: =Historicals!G29 -> 136.05 | E68: =E67*E69 -> 147.78561 | F68: =F67*F69 -> 238.60316 | G68: =G67*G69 -> 331.43685
B69: (Effective Tax Rate) | E69: 0.255 | F69: =E69 -> 0.255 | G69: =F69 -> 0.255 | H69: Normalized 25.5% (22% concessional regime + cess)
B70: Profit After Tax | D70: =D67-D68 -> 3090.67 | E70: =E67-E68 -> 431.7658 | F70: =F67-F68 -> 697.0955 | G70: =G67-G68 -> 968.31549
B71: PAT Margin (%) | D71: =D70/D40 -> 0.25866854 | E71: =E70/E40 -> 0.043128015 | F71: =F70/F40 -> 0.057521586 | G71: =G70/G40 -> 0.065758127
B72: EPS (₹) | D72: =Historicals!G51 -> 6.82 | E72: =E70/36.798 -> 11.733404 | F72: =F70/36.798 -> 18.943842 | G72: =G70/36.798 -> 26.314351 | H72: Shares Outstanding: 36.798 Cr (post-IPO, no further dilution)
B75: PROJECTED BALANCE SHEET (₹ Cr)
B77: Equity & Liabilities
B78: Total Equity (rollforward) | D78: =Historicals!G99 -> 5450.58 | E78: =D78+E70-E79 -> 5771.9518 | F78: =E78+F70-F79 -> 6321.8553 | G78: =F78+G70-G79 -> 7106.1808
B79: (less: Dividends paid) | E79: =3*36.798 -> 110.394 | F79: =4*36.798 -> 147.192 | G79: =5*36.798 -> 183.99 | H79: DPS: FY27 ₹3, FY28 ₹4, FY29 ₹5. Growing absolute DPS with PAT recovery.
B81: Net Debt Drawdown / (Repayment) | E81: 0 | F81: -200 | G81: -300 | H81: FY27: maintained for WC. FY28-29: net repayment from FCF. (Includes WC loans)
B85: Total Debt (incl WC loans) — closing | D85: =Historicals!G216 -> 3538.27 | E85: =D85+E81 -> 3538.27 | F85: =E85+F81 -> 3338.27 | G85: =F85+G81 -> 3038.27
B87: Working Capital Items (Days × Revenue ÷ 365)
B88: Trade Receivables (Days) | D88: =Historicals!G223*365/Historicals!G8 -> 123.35587 | E88: 118 | F88: 110 | G88: 102 | H88: FY26 base 123d. Mgmt 'collection focus FY27' — gradual 5d/yr improvement. 118d/110d/102d.
B89: Contract Assets (Unbilled) (Days) | D89: =Historicals!G224*365/Historicals!G8 -> 236.18244 | E89: 228 | F89: 215 | G89: 200 | H89: FY26 base 236d. Long-cycle Metro+Hydro keeps high. Slow normalize 228d/215d/200d.
B90: Inventories (Days) | D90: =Historicals!G79*365/Historicals!G8 -> 31.054256 | E90: 30 | F90: 30 | G90: 28 | H90: FY26 base 31d. Stable; slight improvement on scale.
B91: Trade Payables (Days) | D91: =Historicals!G218*365/Historicals!G8 -> 136.57066 | E91: 130 | F91: 122 | G91: 115 | H91: FY26 base 137d. Mgmt: 'supplier negotiation post-IPO' → tightening. 130/122/115d.
B92: Contract Liabilities (Advances) (Days) | D92: =Historicals!G219*365/Historicals!G8 -> 125.06382 | E92: 130 | F92: 132 | G92: 135 | H92: FY26 base 125d. Mgmt: 'more advance-heavy overseas contracts' → growing.
B94: Working Capital Items (₹ Cr)
B95: Trade Receivables | D95: =Historicals!G223 -> 4038.09 | E95: =E88*E40/365 -> 3236.5171 | F95: =F88*F40/365 -> 3652.2563 | G95: =G88*G40/365 -> 4115.0465
B96: Contract Assets | D96: =Historicals!G224 -> 7731.5 | E96: =E89*E40/365 -> 6253.6094 | F96: =F89*F40/365 -> 7138.501 | G96: =G89*G40/365 -> 8068.7187
B97: Inventories | D97: =Historicals!G79 -> 1016.57 | E97: =E90*E40/365 -> 822.84334 | F97: =F90*F40/365 -> 996.06991 | G97: =G90*G40/365 -> 1129.6206
B98: Trade Payables | D98: =Historicals!G218 -> 4470.68 | E98: =E91*E40/365 -> 3565.6545 | F98: =F91*F40/365 -> 4050.6843 | G98: =G91*G40/365 -> 4639.5132
B99: Contract Liabilities | D99: =Historicals!G219 -> 4094 | E99: =E92*E40/365 -> 3565.6545 | F99: =F92*F40/365 -> 4382.7076 | G99: =G92*G40/365 -> 5446.3851
B101: Other Balance Sheet Items (held stable or modest growth)
B102: Lease Liabilities | D102: =Historicals!G217 -> 88.64 | E102: =D102 -> 88.64 | F102: =D102 -> 88.64 | G102: =D102 -> 88.64 | H102: Stable assumption
B103: Other Financial Liab | D103: =Historicals!G220 -> 1057.25 | E103: 800 | F103: 700 | G103: 600 | H103: FY26 ₹1,057 elevated; revert to normal
B104: Provisions | D104: =Historicals!G221 -> 219.99 | E104: =D104*1.05 -> 230.9895 | F104: =E104*1.05 -> 242.53897 | G104: =F104*1.05 -> 254.66592 | H104: +5%/yr
B105: Tax Liab (net) | D105: =Historicals!G125 -> 75.68 | E105: =D105 -> 75.68 | F105: =D105 -> 75.68 | G105: =D105 -> 75.68
B106: Other Liab | D106: =Historicals!G126 -> 130.33 | E106: =D106 -> 130.33 | F106: =D106 -> 130.33 | G106: =D106 -> 130.33
B108: Total Liabilities | D108: =D85+D102+D98+D99+D103+D104+D105+D106 -> 13674.84 | E108: =E85+E102+E98+E99+E103+E104+E105+E106 -> 11995.218 | F108: =F85+F102+F98+F99+F103+F104+F105+F106 -> 13008.851 | G108: =G85+G102+G98+G99+G103+G104+G105+G106 -> 14273.484
B109: Total Equity & Liabilities | D109: =D78+D108 -> 19125.42 | E109: =E78+E108 -> 17767.17 | F109: =F78+F108 -> 19330.706 | G109: =G78+G108 -> 21379.665
B111: Assets
B112: Tangible Assets (PPE + CWIP + ROU) | D112: =Historicals!G222 -> 3399.34 | E112: =D112+725-E61 -> 3723.8896 | F112: =E112+600-F61 -> 3863.3733 | G112: =F112+600-G61 -> 3933.2584 | H112: Prior + Capex - D&A. FY27 Rs 725 Cr per mgmt guidance. FY28-29: Rs 600 Cr steady-state.
B113: Intangible Assets | D113: =Historicals!G68 -> 0.5 | E113: =D113 -> 0.5 | F113: =D113 -> 0.5 | G113: =D113 -> 0.5
B114: Investments | D114: =Historicals!G70 -> 0.54 | E114: =D114 -> 0.54 | F114: =D114 -> 0.54 | G114: =D114 -> 0.54
B115: Trade Receivables | D115: =D95 -> 4038.09 | E115: =E95 -> 3236.5171 | F115: =F95 -> 3652.2563 | G115: =G95 -> 4115.0465
B116: Contract Assets (Unbilled) | D116: =D96 -> 7731.5 | E116: =E96 -> 6253.6094 | F116: =F96 -> 7138.501 | G116: =G96 -> 8068.7187
B117: Inventories | D117: =D97 -> 1016.57 | E117: =E97 -> 822.84334 | F117: =F97 -> 996.06991 | G117: =G97 -> 1129.6206
B118: Cash & Bank Balance (PLUG) | D118: =Historicals!G225 -> 885.89 | E118: =E109-E112-E113-E114-E115-E116-E117-E119-E120-E121-E122 -> 1670.9608 | F118: =F109-F112-F113-F114-F115-F116-F117-F119-F120-F121-F122 -> 1621.1557 | G118: =G109-G112-G113-G114-G115-G116-G117-G119-G120-G121-G122 -> 2073.6708 | H118: PLUG: balances BS. Cash = Tot E&L - all other assets.
B119: Loans & Advances | D119: =Historicals!G84 -> 67.93 | E119: =D119 -> 67.93 | F119: =D119 -> 67.93 | G119: =D119 -> 67.93
B120: Other Financial Assets | D120: =Historicals!G226 -> 638.74 | E120: =D120 -> 638.74 | F120: =D120 -> 638.74 | G120: =D120 -> 638.74
B121: Non-current Tax Assets | D121: =Historicals!G74 -> 62.33 | E121: =D121 -> 62.33 | F121: =D121 -> 62.33 | G121: =D121 -> 62.33
B122: Other Assets | D122: =Historicals!G227 -> 1289.31 | E122: =D122 -> 1289.31 | F122: =D122 -> 1289.31 | G122: =D122 -> 1289.31
B123: Total Assets | D123: =SUM(D112:D122) -> 19130.74 | E123: =SUM(E112:E122) -> 17767.17 | F123: =SUM(F112:F122) -> 19330.706 | G123: =SUM(G112:G122) -> 21379.665
B125: BS Tie: Assets - (Eq+Liab) | D125: =D123-D109 -> 5.32 | E125: =E123-E109 -> 0 | F125: =F123-F109 -> 0 | G125: =G123-G109 -> 0 | H125: Should be 0 (cash is plug)
B128: PROJECTED CASH FLOW (₹ Cr)
B130: Profit After Tax | D130: =D70 -> 3090.67 | E130: =E70 -> 431.7658 | F130: =F70 -> 697.0955 | G130: =G70 -> 968.31549
B131: Add: Depreciation | D131: =D61 -> 453.92 | E131: =E61 -> 400.45042 | F131: =F61 -> 460.51632 | G131: =G61 -> 530.11482
B132: Add: Finance Cost | D132: =D64 -> 673.61 | E132: =E64 -> 371.51835 | F132: =F64 -> 361.01835 | G132: =G64 -> 334.76835
B133: Less: Change in WC | D133: =Historicals!G237 -> -1592.2 | E133: =-((E95+E96+E97)-(D95+D96+D97))+((E98+E99)-(D98+D99)) -> 1039.8191 | F133: =-((F95+F96+F97)-(E95+E96+E97))+((F98+F99)-(E98+E99)) -> -171.77446 | G133: =-((G95+G96+G97)-(F95+F96+F97))+((G98+G99)-(F98+F99)) -> 125.9479 | H133: Negative = increase in WC = use of cash
...

Sheet Valuation
B2: AFCONS INFRASTRUCTURE — VALUATION
B3: DCF (6-year explicit + Gordon TV) and Relative Valuation
B5: DISCOUNTED CASH FLOW (DCF)
B7: Cost of Capital Build
B8: Risk-Free Rate (10Y G-Sec) | C8: 0.068 | D8: RBI 10Y G-Sec yield as of May 2026
B9: Equity Risk Premium (India) | C9: 0.06 | D9: Damodaran 2026 India ERP
B10: Beta (Levered) | C10: 1.05 | D10: EPC peer regression
B11: Cost of Equity (Ke) [CAPM] | C11: =C8+C10*C9 -> 0.131 | D11: Rf + Beta × ERP
B12: Pre-tax Cost of Debt (Kd) | C12: 0.105 | D12: Same as model assumption (constant)
B13: Effective Tax Rate | C13: 0.255 | D13: Concessional regime
B14: After-tax Cost of Debt | C14: =C12*(1-C13) -> 0.078225 | D14: Kd × (1−T)
B15: Target D / (D+E) | C15: 0.15 | D15: Conservative target leverage post-IPO
B16: Target E / (D+E) | C16: =1-C15 -> 0.85 | D16: 1 − D/(D+E)
B17: WACC | C17: =C16*C11+C15*C14 -> 0.12308375 | D17: Weighted average
B18: Terminal Growth (g) | C18: 0.04 | D18: India LT nominal GDP × moderation factor
B21: FCFF Projection (₹ Cr)
C22: FY27E | D22: FY28E | E22: FY29E | F22: FY30E | G22: FY31E | H22: FY32E
B23: FCFF | C23: =Projections!E159 -> 1423.8165 | D23: =Projections!F159 -> 654.79604 | E23: =Projections!G159 -> 1273.7806 | F23: =E23*(1+F24) -> 1426.6343 | G23: =F23*(1+G24) -> 1569.2977 | H23: =G23*(1+H24) -> 1694.8415
B24: Growth rate (input for FY30-32) | F24: 0.12 | G24: 0.1 | H24: 0.08
B25: Terminal Value (at FY32) | H25: =H23*(1+C18)/(C17-C18) -> 21215.162
B26: Year (from valuation date) | C26: 1 | D26: 2 | E26: 3 | F26: 4 | G26: 5 | H26: 6
B27: Discount Factor | C27: =1/(1+$C$17)^C26 -> 0.89040555 | D27: =1/(1+$C$17)^D26 -> 0.79282204 | E27: =1/(1+$C$17)^E26 -> 0.70593314 | F27: =1/(1+$C$17)^F26 -> 0.62856678 | G27: =1/(1+$C$17)^G26 -> 0.55967935 | H27: =1/(1+$C$17)^H26 -> 0.4983416
B28: PV of FCFF | C28: =C23*C27 -> 1267.7741 | D28: =D23*D27 -> 519.13673 | E28: =E23*E27 -> 899.20396 | F28: =F23*F27 -> 896.73493 | G28: =G23*G27 -> 878.30353 | H28: =H23*H27 -> 844.61004
B29: PV of Terminal Value | H29: =H25*H27 -> 10572.398
B32: DCF Valuation Summary
B33: Sum of PV(FCFF) FY27-32 | C33: =SUM(C28:H28) -> 5305.7633
B34: PV of Terminal Value | C34: =H29 -> 10572.398
B35: Enterprise Value (EV) | C35: =C33+C34 -> 15878.161
B36: Less: Net Debt (FY26) | C36: =-(Historicals!G216-Historicals!G225) -> -2652.38
B37: Equity Value | C37: =C35+C36 -> 13225.781
B38: Shares Outstanding (Cr) | C38: 36.798
B39: DCF Implied Price (₹/share) | C39: =C37/C38 -> 359.41576
B40: Current Market Price (₹) | C40: 305.45
B41: Upside / (Downside) | C41: =C39/C40-1 -> 0.17667623
B43: DCF Sensitivity — Implied Price (₹) | WACC (cols) × Terminal Growth (rows)
B45: g \ WACC → | D45: =$C$17+-0.015 -> 0.10808375 | E45: =$C$17+-0.01 -> 0.11308375 | F45: =$C$17+-0.005 -> 0.11808375 | G45: =$C$17+0 -> 0.12308375 | H45: =$C$17+0.005 -> 0.12808375 | I45: =$C$17+0.01 -> 0.13308375 | J45: =$C$17+0.015 -> 0.13808375
B46: 0.03 | D46: =($C$23/(1+($C$17+-0.015))^1+$D$23/(1+($C$17+-0.015))^2+$E$23/(1+($C$17+-0.015))^3+$F$23/(1+($C$17+-0.015))^4+$G$23/(1+($C$17+-0.015))^5+$H$23/(1+($C$17+-0.015))^6+($H$23*(1+$B46)/(($C$17+-0.015)-$B46))/(1+($C$17+-0.015))^6-(Historicals!G216-Historicals!G225))/C38 -> 407.10395 | E46: =($C$23/(1+($C$17+-0.01))^1+$D$23/(1+($C$17+-0.01))^2+$E$23/(1+($C$17+-0.01))^3+$F$23/(1+($C$17+-0.01))^4+$G$23/(1+($C$17+-0.01))^5+$H$23/(1+($C$17+-0.01))^6+($H$23*(1+$B46)/(($C$17+-0.01)-$B46))/(1+($C$17+-0.01))^6-(Historicals!G216-Historicals!G225))/C38 -> 376.81337 | F46: =($C$23/(1+($C$17+-0.005))^1+$D$23/(1+($C$17+-0.005))^2+$E$23/(1+($C$17+-0.005))^3+$F$23/(1+($C$17+-0.005))^4+$G$23/(1+($C$17+-0.005))^5+$H$23/(1+($C$17+-0.005))^6+($H$23*(1+$B46)/(($C$17+-0.005)-$B46))/(1+($C$17+-0.005))^6-(Historicals!G216-Historicals!G225))/C38 -> 349.99351 | G46: =($C$23/(1+($C$17+0))^1+$D$23/(1+($C$17+0))^2+$E$23/(1+($C$17+0))^3+$F$23/(1+($C$17+0))^4+$G$23/(1+($C$17+0))^5+$H$23/(1+($C$17+0))^6+($H$23*(1+$B46)/(($C$17+0)-$B46))/(1+($C$17+0))^6-(Historicals!G216-Historicals!G225))/C38 -> 326.08431 | H46: =($C$23/(1+($C$17+0.005))^1+$D$23/(1+($C$17+0.005))^2+$E$23/(1+($C$17+0.005))^3+$F$23/(1+($C$17+0.005))^4+$G$23/(1+($C$17+0.005))^5+$H$23/(1+($C$17+0.005))^6+($H$23*(1+$B46)/(($C$17+0.005)-$B46))/(1+($C$17+0.005))^6-(Historicals!G216-Historicals!G225))/C38 -> 304.63991 | I46: =($C$23/(1+($C$17+0.01))^1+$D$23/(1+($C$17+0.01))^2+$E$23/(1+($C$17+0.01))^3+$F$23/(1+($C$17+0.01))^4+$G$23/(1+($C$17+0.01))^5+$H$23/(1+($C$17+0.01))^6+($H$23*(1+$B46)/(($C$17+0.01)-$B46))/(1+($C$17+0.01))^6-(Historicals!G216-Historicals!G225))/C38 -> 285.30102 | J46: =($C$23/(1+($C$17+0.015))^1+$D$23/(1+($C$17+0.015))^2+$E$23/(1+($C$17+0.015))^3+$F$23/(1+($C$17+0.015))^4+$G$23/(1+($C$17+0.015))^5+$H$23/(1+($C$17+0.015))^6+($H$23*(1+$B46)/(($C$17+0.015)-$B46))/(1+($C$17+0.015))^6-(Historicals!G216-Historicals!G225))/C38 -> 267.7748
B47: 0.035 | D47: =($C$23/(1+($C$17+-0.015))^1+$D$23/(1+($C$17+-0.015))^2+$E$23/(1+($C$17+-0.015))^3+$F$23/(1+($C$17+-0.015))^4+$G$23/(1+($C$17+-0.015))^5+$H$23/(1+($C$17+-0.015))^6+($H$23*(1+$B47)/(($C$17+-0.015)-$B47))/(1+($C$17+-0.015))^6-(Historicals!G216-Historicals!G225))/C38 -> 431.26025 | E47: =($C$23/(1+($C$17+-0.01))^1+$D$23/(1+($C$17+-0.01))^2+$E$23/(1+($C$17+-0.01))^3+$F$23/(1+($C$17+-0.01))^4+$G$23/(1+($C$17+-0.01))^5+$H$23/(1+($C$17+-0.01))^6+($H$23*(1+$B47)/(($C$17+-0.01)-$B47))/(1+($C$17+-0.01))^6-(Historicals!G216-Historicals!G225))/C38 -> 397.58923 | F47: =($C$23/(1+($C$17+-0.005))^1+$D$23/(1+($C$17+-0.005))^2+$E$23/(1+($C$17+-0.005))^3+$F$23/(1+($C$17+-0.005))^4+$G$23/(1+($C$17+-0.005))^5+$H$23/(1+($C$17+-0.005))^6+($H$23*(1+$B47)/(($C$17+-0.005)-$B47))/(1+($C$17+-0.005))^6-(Historicals!G216-Historicals!G225))/C38 -> 368.00258 | G47: =($C$23/(1+($C$17+0))^1+$D$23/(1+($C$17+0))^2+$E$23/(1+($C$17+0))^3+$F$23/(1+($C$17+0))^4+$G$23/(1+($C$17+0))^5+$H$23/(1+($C$17+0))^6+($H$23*(1+$B47)/(($C$17+0)-$B47))/(1+($C$17+0))^6-(Historicals!G216-Historicals!G225))/C38 -> 341.80401 | H47: =($C$23/(1+($C$17+0.005))^1+$D$23/(1+($C$17+0.005))^2+$E$23/(1+($C$17+0.005))^3+$F$23/(1+($C$17+0.005))^4+$G$23/(1+($C$17+0.005))^5+$H$23/(1+($C$17+0.005))^6+($H$23*(1+$B47)/(($C$17+0.005)-$B47))/(1+($C$17+0.005))^6-(Historicals!G216-Historicals!G225))/C38 -> 318.44685 | I47: =($C$23/(1+($C$17+0.01))^1+$D$23/(1+($C$17+0.01))^2+$E$23/(1+($C$17+0.01))^3+$F$23/(1+($C$17+0.01))^4+$G$23/(1+($C$17+0.01))^5+$H$23/(1+($C$17+0.01))^6+($H$23*(1+$B47)/(($C$17+0.01)-$B47))/(1+($C$17+0.01))^6-(Historicals!G216-Historicals!G225))/C38 -> 297.4959 | J47: =($C$23/(1+($C$17+0.015))^1+$D$23/(1+($C$17+0.015))^2+$E$23/(1+($C$17+0.015))^3+$F$23/(1+($C$17+0.015))^4+$G$23/(1+($C$17+0.015))^5+$H$23/(1+($C$17+0.015))^6+($H$23*(1+$B47)/(($C$17+0.015)-$B47))/(1+($C$17+0.015))^6-(Historicals!G216-Historicals!G225))/C38 -> 278.60043
B48: 0.04 | D48: =($C$23/(1+($C$17+-0.015))^1+$D$23/(1+($C$17+-0.015))^2+$E$23/(1+($C$17+-0.015))^3+$F$23/(1+($C$17+-0.015))^4+$G$23/(1+($C$17+-0.015))^5+$H$23/(1+($C$17+-0.015))^6+($H$23*(1+$B48)/(($C$17+-0.015)-$B48))/(1+($C$17+-0.015))^6-(Historicals!G216-Historicals!G225))/C38 -> 458.96458 | E48: =($C$23/(1+($C$17+-0.01))^1+$D$23/(1+($C$17+-0.01))^2+$E$23/(1+($C$17+-0.01))^3+$F$23/(1+($C$17+-0.01))^4+$G$23/(1+($C$17+-0.01))^5+$H$23/(1+($C$17+-0.01))^6+($H$23*(1+$B48)/(($C$17+-0.01)-$B48))/(1+($C$17+-0.01))^6-(Historicals!G216-Historicals!G225))/C38 -> 421.20783 | F48: =($C$23/(1+($C$17+-0.005))^1+$D$23/(1+($C$17+-0.005))^2+$E$23/(1+($C$17+-0.005))^3+$F$23/(1+($C$17+-0.005))^4+$G$23/(1+($C$17+-0.005))^5+$H$23/(1+($C$17+-0.005))^6+($H$23*(1+$B48)/(($C$17+-0.005)-$B48))/(1+($C$17+-0.005))^6-(Historicals!G216-Historicals!G225))/C38 -> 388.31803 | G48: =($C$23/(1+($C$17+0))^1+$D$23/(1+($C$17+0))^2+$E$23/(1+($C$17+0))^3+$F$23/(1+($C$17+0))^4+$G$23/(1+($C$17+0))^5+$H$23/(1+($C$17+0))^6+($H$23*(1+$B48)/(($C$17+0)-$B48))/(1+($C$17+0))^6-(Historicals!G216-Historicals!G225))/C38 -> 359.41576 | H48: =($C$23/(1+($C$17+0.005))^1+$D$23/(1+($C$17+0.005))^2+$E$23/(1+($C$17+0.005))^3+$F$23/(1+($C$17+0.005))^4+$G$23/(1+($C$17+0.005))^5+$H$23/(1+($C$17+0.005))^6+($H$23*(1+$B48)/(($C$17+0.005)-$B48))/(1+($C$17+0.005))^6-(Historicals!G216-Historicals!G225))/C38 -> 333.82126 | I48: =($C$23/(1+($C$17+0.01))^1+$D$23/(1+($C$17+0.01))^2+$E$23/(1+($C$17+0.01))^3+$F$23/(1+($C$17+0.01))^4+$G$23/(1+($C$17+0.01))^5+$H$23/(1+($C$17+0.01))^6+($H$23*(1+$B48)/(($C$17+0.01)-$B48))/(1+($C$17+0.01))^6-(Historicals!G216-Historicals!G225))/C38 -> 311.00087 | J48: =($C$23/(1+($C$17+0.015))^1+$D$23/(1+($C$17+0.015))^2+$E$23/(1+($C$17+0.015))^3+$F$23/(1+($C$17+0.015))^4+$G$23/(1+($C$17+0.015))^5+$H$23/(1+($C$17+0.015))^6+($H$23*(1+$B48)/(($C$17+0.015)-$B48))/(1+($C$17+0.015))^6-(Historicals!G216-Historicals!G225))/C38 -> 290.52977
B49: 0.045 | D49: =($C$23/(1+($C$17+-0.015))^1+$D$23/(1+($C$17+-0.015))^2+$E$23/(1+($C$17+-0.015))^3+$F$23/(1+($C$17+-0.015))^4+$G$23/(1+($C$17+-0.015))^5+$H$23/(1+($C$17+-0.015))^6+($H$23*(1+$B49)/(($C$17+-0.015)-$B49))/(1+($C$17+-0.015))^6-(Historicals!G216-Historicals!G225))/C38 -> 491.06059 | E49: =($C$23/(1+($C$17+-0.01))^1+$D$23/(1+($C$17+-0.01))^2+$E$23/(1+($C$17+-0.01))^3+$F$23/(1+($C$17+-0.01))^4+$G$23/(1+($C$17+-0.01))^5+$H$23/(1+($C$17+-0.01))^6+($H$23*(1+$B49)/(($C$17+-0.01)-$B49))/(1+($C$17+-0.01))^6-(Historicals!G216-Historicals!G225))/C38 -> 448.29548 | F49: =($C$23/(1+($C$17+-0.005))^1+$D$23/(1+($C$17+-0.005))^2+$E$23/(1+($C$17+-0.005))^3+$F$23/(1+($C$17+-0.005))^4+$G$23/(1+($C$17+-0.005))^5+$H$23/(1+($C$17+-0.005))^6+($H$23*(1+$B49)/(($C$17+-0.005)-$B49))/(1+($C$17+-0.005))^6-(Historicals!G216-Historicals!G225))/C38 -> 411.41323 | G49: =($C$23/(1+($C$17+0))^1+$D$23/(1+($C$17+0))^2+$E$23/(1+($C$17+0))^3+$F$23/(1+($C$17+0))^4+$G$23/(1+($C$17+0))^5+$H$23/(1+($C$17+0))^6+($H$23*(1+$B49)/(($C$17+0)-$B49))/(1+($C$17+0))^6-(Historicals!G216-Historicals!G225))/C38 -> 379.28299 | H49: =($C$23/(1+($C$17+0.005))^1+$D$23/(1+($C$17+0.005))^2+$E$23/(1+($C$17+0.005))^3+$F$23/(1+($C$17+0.005))^4+$G$23/(1+($C$17+0.005))^5+$H$23/(1+($C$17+0.005))^6+($H$23*(1+$B49)/(($C$17+0.005)-$B49))/(1+($C$17+0.005))^6-(Historicals!G216-Historicals!G225))/C38 -> 351.04614 | I49: =($C$23/(1+($C$17+0.01))^1+$D$23/(1+($C$17+0.01))^2+$E$23/(1+($C$17+0.01))^3+$F$23/(1+($C$17+0.01))^4+$G$23/(1+($C$17+0.01))^5+$H$23/(1+($C$17+0.01))^6+($H$23*(1+$B49)/(($C$17+0.01)-$B49))/(1+($C$17+0.01))^6-(Historicals!G216-Historicals!G225))/C38 -> 326.03905 | J49: =($C$23/(1+($C$17+0.015))^1+$D$23/(1+($C$17+0.015))^2+$E$23/(1+($C$17+0.015))^3+$F$23/(1+($C$17+0.015))^4+$G$23/(1+($C$17+0.015))^5+$H$23/(1+($C$17+0.015))^6+($H$23*(1+$B49)/(($C$17+0.015)-$B49))/(1+($C$17+0.015))^6-(Historicals!G216-Historicals!G225))/C38 -> 303.74069
B50: 0.05 | D50: =($C$23/(1+($C$17+-0.015))^1+$D$23/(1+($C$17+-0.015))^2+$E$23/(1+($C$17+-0.015))^3+$F$23/(1+($C$17+-0.015))^4+$G$23/(1+($C$17+-0.015))^5+$H$23/(1+($C$17+-0.015))^6+($H$23*(1+$B50)/(($C$17+-0.015)-$B50))/(1+($C$17+-0.015))^6-(Historicals!G216-Historicals!G225))/C38 -> 528.68241 | E50: =($C$23/(1+($C$17+-0.01))^1+$D$23/(1+($C$17+-0.01))^2+$E$23/(1+($C$17+-0.01))^3+$F$23/(1+($C$17+-0.01))^4+$G$23/(1+($C$17+-0.01))^5+$H$23/(1+($C$17+-0.01))^6+($H$23*(1+$B50)/(($C$17+-0.01)-$B50))/(1+($C$17+-0.01))^6-(Historicals!G216-Historicals!G225))/C38 -> 479.67706 | F50: =($C$23/(1+($C$17+-0.005))^1+$D$23/(1+($C$17+-0.005))^2+$E$23/(1+($C$17+-0.005))^3+$F$23/(1+($C$17+-0.005))^4+$G$23/(1+($C$17+-0.005))^5+$H$23/(1+($C$17+-0.005))^6+($H$23*(1+$B50)/(($C$17+-0.005)-$B50))/(1+($C$17+-0.005))^6-(Historicals!G216-Historicals!G225))/C38 -> 437.90061 | G50: =($C$23/(1+($C$17+0))^1+$D$23/(1+($C$17+0))^2+$E$23/(1+($C$17+0))^3+$F$23/(1+($C$17+0))^4+$G$23/(1+($C$17+0))^5+$H$23/(1+($C$17+0))^6+($H$23*(1+$B50)/(($C$17+0)-$B50))/(1+($C$17+0))^6-(Historicals!G216-Historicals!G225))/C38 -> 401.86864 | H50: =($C$23/(1+($C$17+0.005))^1+$D$23/(1+($C$17+0.005))^2+$E$23/(1+($C$17+0.005))^3+$F$23/(1+($C$17+0.005))^4+$G$23/(1+($C$17+0.005))^5+$H$23/(1+($C$17+0.005))^6+($H$23*(1+$B50)/(($C$17+0.005)-$B50))/(1+($C$17+0.005))^6-(Historicals!G216-Historicals!G225))/C38 -> 370.47697 | I50: =($C$23/(1+($C$17+0.01))^1+$D$23/(1+($C$17+0.01))^2+$E$23/(1+($C$17+0.01))^3+$F$23/(1+($C$17+0.01))^4+$G$23/(1+($C$17+0.01))^5+$H$23/(1+($C$17+0.01))^6+($H$23*(1+$B50)/(($C$17+0.01)-$B50))/(1+($C$17+0.01))^6-(Historicals!G216-Historicals!G225))/C38 -> 342.88723 | J50: =($C$23/(1+($C$17+0.015))^1+$D$23/(1+($C$17+0.015))^2+$E$23/(1+($C$17+0.015))^3+$F$23/(1+($C$17+0.015))^4+$G$23/(1+($C$17+0.015))^5+$H$23/(1+($C$17+0.015))^6+($H$23*(1+$B50)/(($C$17+0.015)-$B50))/(1+($C$17+0.015))^6-(Historicals!G216-Historicals!G225))/C38 -> 318.45141
B53: RELATIVE VALUATION
B55: Peer Multiples (May 2026)
B56: Company | C56: P/E (x) | D56: P/B (x) | E56: EV/EBITDA (x) | F56: EBITDA Margin
B57: Larsen & Toubro | C57: 34.3 | D57: 3.5 | E57: 20.3 | F57: 0.1 | G57: Note: diversified, excluded from median
B58: KEC International | C58: 20.7 | D58: 2 | E58: 11.5 | F58: 0.075 | G58: T&D + railway
B59: Kalpataru Projects (KPIL) | C59: 30.2 | D59: 2.5 | E59: 12.2 | F59: 0.085 | G59: T&D + civil
B60: NCC Ltd | C60: 14.1 | D60: 1.3 | E60: 7.8 | F60: 0.087 | G60: Buildings + roads
B61: Ircon International | C61: 25.6 | D61: 2.4 | E61: 18.5 | F61: 0.085 | G61: Railway PSU
B62: Peer Median (excl L&T) | C62: =MEDIAN(C58:C61) -> 23.15 | D62: =MEDIAN(D58:D61) -> 2.2 | E62: =MEDIAN(E58:E61) -> 11.85 | F62: =MEDIAN(F58:F61) -> 0.085
B63: Afcons (Current) | C63: =(C40*C38)/Historicals!G31 -> 44.827108 | D63: =(C40*C38)/Historicals!G99 -> 2.0621565 | E63: =((C40*C38)+(Historicals!G216-Historicals!G225))/Historicals!G210 -> 11.414194 | F63: =Historicals!G210/Historicals!G8 -> 0.10186402
B66: Target Multiples & Implied Price
B67: Multiple | C67: Target | D67: Forward Metric | E67: Implied Price (₹) | F67: Rationale
B68: EV/EBITDA (FY28E) | C68: 11 | D68: =Projections!F58 -> 1393.6678 | E68: =(C68*D68-(Historicals!G216-Historicals!G225))/C38 -> 344.52867 | F68: Peer median ~12x; slight discount for execution risk
B69: P/E (FY28E) | C69: 20 | D69: =Projections!F70 -> 697.0955 | E69: =C69*D69/C38 -> 378.87684 | F69: Peer median ~25x; small-cap discount
B70: P/B (FY26) | C70: 1.8 | D70: =Historicals!G99 -> 5450.58 | E70: =C70*D70/C38 -> 266.61895 | F70: Peer median ~2.4x
B73: Blended Target Price
B74: Method | C74: Implied Price (₹) | D74: Weight | E74: Weighted (₹)
B75: DCF | C75: =C39 -> 359.41576 | D75: 0.4 | E75: =C75*D75 -> 143.7663
B76: EV/EBITDA (FY28E) | C76: =E68 -> 344.52867 | D76: 0.3 | E76: =C76*D76 -> 103.3586
B77: P/E (FY28E) | C77: =E69 -> 378.87684 | D77: 0.2 | E77: =C77*D77 -> 75.775369
B78: P/B (FY26) | C78: =E70 -> 266.61895 | D78: 0.1 | E78: =C78*D78 -> 26.661895
B79: BLENDED TARGET PRICE | C79: Sum → | D79: =SUM(D75:D78) -> 1 | E79: =SUM(E75:E78) -> 349.56217
B81: Current Market Price (₹) | E81: =C40 -> 305.45
B82: Implied Upside / (Downside) | E82: =E79/E81-1 -> 0.14441698
B83: Recommendation | E83: =IF(E82>0.15,"BUY",IF(E82>0,"HOLD","SELL")) -> HOLD
